{
    "CFG": {
        "BRANCH": "WRLINUX_10_22_BASE_UPDATE0008",
        "CACHE": "config/index-cache/layers_wrs_com",
        "DESCRIPTION": "Wind River Developer Layer Index",
        "TYPE": "restapi-web",
        "URL": "http://layers.wrs.com/layerindex/api/"
    },
    "YPCompatibleVersions": [
        {
            "description": "",
            "id": 2,
            "image_url": "",
            "link_url": "",
            "name": "thud wrl"
        },
        {
            "description": "",
            "id": 3,
            "image_url": "",
            "link_url": "",
            "name": "thud"
        },
        {
            "description": "",
            "id": 4,
            "image_url": "",
            "link_url": "",
            "name": "sumo thud"
        },
        {
            "description": "",
            "id": 5,
            "image_url": "",
            "link_url": "",
            "name": "rocko"
        },
        {
            "description": "",
            "id": 6,
            "image_url": "",
            "link_url": "",
            "name": "rocko sumo thud"
        },
        {
            "description": "",
            "id": 7,
            "image_url": "",
            "link_url": "",
            "name": "sumo thud wrl"
        },
        {
            "description": "",
            "id": 8,
            "image_url": "",
            "link_url": "",
            "name": "rocko wrl"
        },
        {
            "description": "",
            "id": 9,
            "image_url": "",
            "link_url": "",
            "name": "thud warrior"
        },
        {
            "description": "",
            "id": 11,
            "image_url": "",
            "link_url": "",
            "name": "thud warrior wrl"
        },
        {
            "description": "",
            "id": 16,
            "image_url": "",
            "link_url": "",
            "name": "sumo"
        },
        {
            "description": "",
            "id": 97,
            "image_url": "",
            "link_url": "",
            "name": "warrior zeus"
        },
        {
            "description": "",
            "id": 98,
            "image_url": "",
            "link_url": "",
            "name": "zeus"
        },
        {
            "description": "",
            "id": 99,
            "image_url": "",
            "link_url": "",
            "name": "thud warrior zeus"
        },
        {
            "description": "",
            "id": 100,
            "image_url": "",
            "link_url": "",
            "name": "wrl zeus"
        },
        {
            "description": "",
            "id": 101,
            "image_url": "",
            "link_url": "",
            "name": "thud warrior wrl zeus"
        },
        {
            "description": "",
            "id": 102,
            "image_url": "",
            "link_url": "",
            "name": "warrior wrl zeus"
        },
        {
            "description": "",
            "id": 103,
            "image_url": "",
            "link_url": "",
            "name": "sumo thud warrior zeus"
        },
        {
            "description": "",
            "id": 275,
            "image_url": "",
            "link_url": "",
            "name": "thud zeus"
        },
        {
            "description": "",
            "id": 1808,
            "image_url": "",
            "link_url": "",
            "name": "thud wrl zeus"
        },
        {
            "description": "",
            "id": 1809,
            "image_url": "",
            "link_url": "",
            "name": "gatesgarth hardknott"
        },
        {
            "description": "",
            "id": 15718,
            "image_url": "",
            "link_url": "",
            "name": "hardknott"
        },
        {
            "description": "",
            "id": 16389,
            "image_url": "",
            "link_url": "",
            "name": "hardknott wrl"
        },
        {
            "description": "",
            "id": 27299,
            "image_url": "",
            "link_url": "",
            "name": "honister"
        },
        {
            "description": "",
            "id": 30256,
            "image_url": "",
            "link_url": "",
            "name": "hardknott honister"
        },
        {
            "description": "",
            "id": 36944,
            "image_url": "",
            "link_url": "",
            "name": "gatesgarth hardknott honi"
        },
        {
            "description": "",
            "id": 42542,
            "image_url": "",
            "link_url": "",
            "name": "2.7 3.0 wrl"
        },
        {
            "description": "",
            "id": 42544,
            "image_url": "",
            "link_url": "",
            "name": "3.3"
        },
        {
            "description": "",
            "id": 42545,
            "image_url": "",
            "link_url": "",
            "name": "3.3 wrl"
        },
        {
            "description": "",
            "id": 42546,
            "image_url": "",
            "link_url": "",
            "name": "3.3 3.4"
        },
        {
            "description": "",
            "id": 42547,
            "image_url": "",
            "link_url": "",
            "name": "3.4"
        },
        {
            "description": "",
            "id": 42549,
            "image_url": "",
            "link_url": "",
            "name": "3.1 3.2 3.3 3.4"
        },
        {
            "description": "",
            "id": 42551,
            "image_url": "",
            "link_url": "",
            "name": "2.4 wrl"
        },
        {
            "description": "",
            "id": 42552,
            "image_url": "",
            "link_url": "",
            "name": "3.2 3.3"
        },
        {
            "description": "",
            "id": 42553,
            "image_url": "",
            "link_url": "",
            "name": "2.6 wrl"
        },
        {
            "description": "",
            "id": 42554,
            "image_url": "",
            "link_url": "",
            "name": "2.6 2.7 3.0 wrl"
        },
        {
            "description": "",
            "id": 42555,
            "image_url": "",
            "link_url": "",
            "name": "2.5 2.6"
        },
        {
            "description": "",
            "id": 42556,
            "image_url": "",
            "link_url": "",
            "name": "2.6 2.7"
        },
        {
            "description": "",
            "id": 42558,
            "image_url": "",
            "link_url": "",
            "name": "2.6"
        },
        {
            "description": "",
            "id": 42559,
            "image_url": "",
            "link_url": "",
            "name": "2.4 2.5 2.6"
        },
        {
            "description": "",
            "id": 42560,
            "image_url": "",
            "link_url": "",
            "name": "2.5 2.6 wrl"
        },
        {
            "description": "",
            "id": 42561,
            "image_url": "",
            "link_url": "",
            "name": "2.6 2.7 3.0"
        },
        {
            "description": "",
            "id": 42562,
            "image_url": "",
            "link_url": "",
            "name": "2.7 3.0"
        },
        {
            "description": "",
            "id": 42563,
            "image_url": "",
            "link_url": "",
            "name": "2.7 3.0 3.1 3.2 3.3"
        },
        {
            "description": "",
            "id": 42564,
            "image_url": "",
            "link_url": "",
            "name": "3.0 wrl"
        },
        {
            "description": "",
            "id": 42565,
            "image_url": "",
            "link_url": "",
            "name": "2.5 2.6 2.7 3.0"
        },
        {
            "description": "",
            "id": 42566,
            "image_url": "",
            "link_url": "",
            "name": "2.4"
        },
        {
            "description": "",
            "id": 42567,
            "image_url": "",
            "link_url": "",
            "name": "3.2 3.3 3.4"
        },
        {
            "description": "",
            "id": 42568,
            "image_url": "",
            "link_url": "",
            "name": "2.6 3.0"
        },
        {
            "description": "",
            "id": 42569,
            "image_url": "",
            "link_url": "",
            "name": "3.0"
        },
        {
            "description": "",
            "id": 42570,
            "image_url": "",
            "link_url": "",
            "name": "2.6 3.0 wrl"
        },
        {
            "description": "",
            "id": 42579,
            "image_url": "",
            "link_url": "",
            "name": "4.0"
        },
        {
            "description": "",
            "id": 42580,
            "image_url": "",
            "link_url": "",
            "name": "4.0 wrl"
        },
        {
            "description": "",
            "id": 42581,
            "image_url": "",
            "link_url": "",
            "name": "3.1 3.2 3.3 3.4 4.0"
        },
        {
            "description": "",
            "id": 42582,
            "image_url": "",
            "link_url": "",
            "name": "3.4 4.0"
        },
        {
            "description": "",
            "id": 42583,
            "image_url": "",
            "link_url": "",
            "name": "3.1 3.3 3.4 4.0"
        },
        {
            "description": "",
            "id": 42585,
            "image_url": "",
            "link_url": "",
            "name": "4.0 4.1"
        },
        {
            "description": "",
            "id": 42588,
            "image_url": "",
            "link_url": "",
            "name": "3.2 3.3 3.4 4.0"
        },
        {
            "description": "",
            "id": 42589,
            "image_url": "",
            "link_url": "",
            "name": "2.7 3.0 3.2 3.3 3.4 4.0"
        },
        {
            "description": "",
            "id": 42590,
            "image_url": "",
            "link_url": "",
            "name": "4.1"
        },
        {
            "description": "",
            "id": 42591,
            "image_url": "",
            "link_url": "",
            "name": "4.1 wrl"
        },
        {
            "description": "",
            "id": 42594,
            "image_url": "",
            "link_url": "",
            "name": "4.1 4.2"
        },
        {
            "description": "",
            "id": 42596,
            "image_url": "",
            "link_url": "",
            "name": "4.2 wrl"
        },
        {
            "description": "",
            "id": 42597,
            "image_url": "",
            "link_url": "",
            "name": "4.2"
        },
        {
            "description": "",
            "id": 42598,
            "image_url": "",
            "link_url": "",
            "name": "4.0 4.1 4.2"
        },
        {
            "description": "",
            "id": 42599,
            "image_url": "",
            "link_url": "",
            "name": "3.1 4.0 4.1 4.2"
        },
        {
            "description": "",
            "id": 44173,
            "image_url": "",
            "link_url": "",
            "name": "3.2 3.3 3.4 4.0 4.1 4.2"
        }
    ],
    "branches": [
        {
            "bitbake_branch": "WRLINUX_10_22_BASE_UPDATE0008",
            "comparison": false,
            "hidden": false,
            "id": 340,
            "name": "WRLINUX_10_22_BASE_UPDATE0008",
            "short_description": "WRLinux 10_22 Base Update 0008",
            "sort_priority": 15,
            "update_environment": null,
            "updated": "2023-04-18T00:04:15+0000",
            "updates_enabled": true
        }
    ],
    "distros": [],
    "layerBranches": [
        {
            "actual_branch": "",
            "branch": 340,
            "collection": "core",
            "id": 940020,
            "layer": 1,
            "local_path": "",
            "updated": "2023-04-18T07:04:55+0000",
            "vcs_last_commit": "2023-04-17T12:04:55+0000",
            "vcs_last_fetch": "2023-04-18T07:04:55+0000",
            "vcs_last_rev": "8e53fe00abfbb24dedb34b1e6f8d02488e7a05e1",
            "vcs_subdir": "meta",
            "version": "14",
            "yp_compatible_version": 42580
        },
        {
            "actual_branch": "",
            "branch": 340,
            "collection": "meta-arm",
            "id": 940047,
            "layer": 474,
            "local_path": "",
            "updated": "2023-04-14T02:04:02+0000",
            "vcs_last_commit": "2023-03-20T00:03:41+0000",
            "vcs_last_fetch": "2023-04-14T02:04:02+0000",
            "vcs_last_rev": "a8a7a2d32900101a91b2b3d92b3bef4d64f91418",
            "vcs_subdir": "meta-arm",
            "version": null,
            "yp_compatible_version": 42579
        }
    ],
    "layerDependencies": [
        {
            "dependency": 1,
            "id": 110266,
            "layerbranch": 940047,
            "required": true
        },
        {
            "dependency": 475,
            "id": 110267,
            "layerbranch": 940047,
            "required": false
        }
    ],
    "layerItems": [
        {
            "collection": "core",
            "comparison": false,
            "description": "OpenEmbedded-Core is a layer containing the core metadata for current versions\r\nof OpenEmbedded. It is distro-less (can build a functional image with\r\nDISTRO = \"nodistro\") and contains only emulated machine support.",
            "id": 1,
            "index_preference": 1000,
            "layer_type": "A",
            "mailing_list_url": "",
            "name": "openembedded-core",
            "status": "P",
            "summary": "Core Metadata",
            "updated": "2018-05-30T23:05:28+0000",
            "usage_url": "README",
            "vcs_url": "#BASE_URL#/oe-core",
            "vcs_web_commit_url": "",
            "vcs_web_file_base_url": "",
            "vcs_web_tree_base_url": "",
            "vcs_web_url": ""
        },
        {
            "collection": "meta-arm",
            "comparison": false,
            "description": "This repository contains the Arm layers for OpenEmbedded.",
            "id": 474,
            "index_preference": 0,
            "layer_type": "B",
            "mailing_list_url": "",
            "name": "meta-arm",
            "status": "P",
            "summary": "This repository contains the Arm layers for OpenEmbedded.",
            "updated": "2022-05-31T02:05:06+0000",
            "usage_url": "",
            "vcs_url": "#BASE_URL#/meta-arm",
            "vcs_web_commit_url": "",
            "vcs_web_file_base_url": "",
            "vcs_web_tree_base_url": "",
            "vcs_web_url": ""
        }
    ],
    "machines": [
        {
            "description": "",
            "id": 64138,
            "layerbranch": 940047,
            "name": "qemuarm64-secureboot",
            "updated": "2023-04-14T02:04:02+0000"
        },
        {
            "description": "Generic Arm64 machine for typical SystemReady platforms, which",
            "id": 64139,
            "layerbranch": 940047,
            "name": "generic-arm64",
            "updated": "2023-04-14T02:04:02+0000"
        },
        {
            "description": "Generic Arm64 machine for typical SystemReady platforms, which",
            "id": 64140,
            "layerbranch": 940047,
            "name": "qemu-generic-arm64",
            "updated": "2023-04-14T02:04:02+0000"
        },
        {
            "description": "Machine for Zephyr BOARD qemu_cortex_a53",
            "id": 64141,
            "layerbranch": 940047,
            "name": "qemu-cortex-a53",
            "updated": "2023-04-14T02:04:02+0000"
        },
        {
            "description": "Machine for BBC Microbit v1, Zephyr BOARD qemu_cortex_m0",
            "id": 64142,
            "layerbranch": 940047,
            "name": "microbit-v1",
            "updated": "2023-04-14T02:04:02+0000"
        }
    ],
    "recipes": [
        {
            "bbclassextend": "native",
            "blacklisted": "",
            "bugtracker": "",
            "configopts": "",
            "description": "",
            "filename": "gn_git.bb",
            "filepath": "recipes-devtools/gn",
            "homepage": "",
            "id": 1752478,
            "inherits": "",
            "layerbranch": 940047,
            "license": "BSD-3-Clause",
            "pe": "",
            "pn": "gn",
            "pr": "r0",
            "provides": "gn ",
            "pv": "0+gitX",
            "section": "base",
            "srcrev": "69ec4fca1fa69ddadae13f9e6b7507efa0675263",
            "summary": "GN is a meta-build system that generates build files for Ninja",
            "updated": "2023-04-14T02:04:59+0000"
        },
        {
            "bbclassextend": "",
            "blacklisted": "",
            "bugtracker": "",
            "configopts": "",
            "description": "fiptool - Trusted Firmware tool for packaging",
            "filename": "fiptool-native_2.5.bb",
            "filepath": "recipes-devtools/fiptool",
            "homepage": "",
            "id": 1752479,
            "inherits": "native nopackages relocatable",
            "layerbranch": 940047,
            "license": "BSD-3-Clause",
            "pe": "",
            "pn": "fiptool-native",
            "pr": "r0",
            "provides": "fiptool-native ",
            "pv": "2.5",
            "section": "base",
            "srcrev": "c158878249f1bd930906ebd744b90d3f2a8265f1",
            "summary": "",
            "updated": "2023-04-14T02:04:59+0000"
        },
        {
            "bbclassextend": "native nativesdk",
            "blacklisted": "",
            "bugtracker": "",
            "configopts": "",
            "description": "",
            "filename": "fvp-corstone1000.bb",
            "filepath": "recipes-devtools/fvp",
            "homepage": "https://developer.arm.com/tools-and-software/open-source-software/arm-platforms-software/arm-ecosystem-fvps",
            "id": 1752480,
            "inherits": "",
            "layerbranch": 940047,
            "license": "Proprietary & Apache-2.0 & Python-2.0 & GPL-3.0-with-GCC-exception & Zlib & NCSA & LGPL-2.0-or-later & MIT & BSD-3-Clause",
            "pe": "",
            "pn": "fvp-corstone1000",
            "pr": "r0",
            "provides": "fvp-corstone1000 ",
            "pv": "11.17_23",
            "section": "base",
            "srcrev": "",
            "summary": "Arm Fixed Virtual Platform - Corstone-1000-23 Ecosystem Reference Design",
            "updated": "2023-04-14T02:04:59+0000"
        },
        {
            "bbclassextend": "native nativesdk",
            "blacklisted": "",
            "bugtracker": "",
            "configopts": "",
            "description": "",
            "filename": "fvp-library.bb",
            "filepath": "recipes-devtools/fvp",
            "homepage": "https://developer.arm.com/tools-and-software/simulation-models/fixed-virtual-platforms",
            "id": 1752481,
            "inherits": "",
            "layerbranch": 940047,
            "license": "Proprietary & Apache-2.0 & Python-2.0 & GPL-3.0-with-GCC-exception & Zlib & NCSA & LGPL-2.0-or-later & MIT & BSD-3-Clause",
            "pe": "",
            "pn": "fvp-library",
            "pr": "r0",
            "provides": "fvp-library ",
            "pv": "11.15_14",
            "section": "base",
            "srcrev": "",
            "summary": "Arm Fixed Virtual Platform - Library Ecosystem Reference Design",
            "updated": "2023-04-14T02:04:00+0000"
        },
        {
            "bbclassextend": "native nativesdk",
            "blacklisted": "",
            "bugtracker": "",
            "configopts": "",
            "description": "",
            "filename": "fvp-n1-edge.bb",
            "filepath": "recipes-devtools/fvp",
            "homepage": "https://developer.arm.com/tools-and-software/open-source-software/arm-platforms-software/arm-ecosystem-fvps",
            "id": 1752482,
            "inherits": "",
            "layerbranch": 940047,
            "license": "Proprietary & Apache-2.0 & Python-2.0 & GPL-3.0-with-GCC-exception & Zlib & NCSA & LGPL-2.0-or-later & MIT & BSD-3-Clause",
            "pe": "",
            "pn": "fvp-n1-edge",
            "pr": "r0",
            "provides": "fvp-n1-edge ",
            "pv": "11.15.26",
            "section": "base",
            "srcrev": "",
            "summary": "Arm Fixed Virtual Platform - Neoverse-N1 Ecosystem Reference Design",
            "updated": "2023-04-14T02:04:00+0000"
        },
        {
            "bbclassextend": "native nativesdk",
            "blacklisted": "",
            "bugtracker": "",
            "configopts": "",
            "description": "",
            "filename": "fvp-sgi575.bb",
            "filepath": "recipes-devtools/fvp",
            "homepage": "https://developer.arm.com/tools-and-software/open-source-software/arm-platforms-software/arm-ecosystem-fvps",
            "id": 1752483,
            "inherits": "",
            "layerbranch": 940047,
            "license": "Proprietary & Apache-2.0 & Python-2.0 & GPL-3.0-with-GCC-exception & Zlib & NCSA & LGPL-2.0-or-later & MIT & BSD-3-Clause",
            "pe": "",
            "pn": "fvp-sgi575",
            "pr": "r0",
            "provides": "fvp-sgi575 ",
            "pv": "11.15.26",
            "section": "base",
            "srcrev": "",
            "summary": "Arm Fixed Virtual Platform - SGI-575 Ecosystem Reference Design",
            "updated": "2023-04-14T02:04:00+0000"
        },
        {
            "bbclassextend": "native nativesdk",
            "blacklisted": "",
            "bugtracker": "",
            "configopts": "",
            "description": "",
            "filename": "fvp-tc0.bb",
            "filepath": "recipes-devtools/fvp",
            "homepage": "https://developer.arm.com/tools-and-software/open-source-software/arm-platforms-software/arm-ecosystem-fvps",
            "id": 1752484,
            "inherits": "",
            "layerbranch": 940047,
            "license": "Proprietary & Apache-2.0 & Python-2.0 & GPL-3.0-with-GCC-exception & Zlib & NCSA & LGPL-2.0-or-later & MIT & BSD-3-Clause",
            "pe": "",
            "pn": "fvp-tc0",
            "pr": "r0",
            "provides": "fvp-tc0 ",
            "pv": "11.15.20",
            "section": "base",
            "srcrev": "",
            "summary": "Arm Fixed Virtual Platform - TotalCompute Ecosystem Reference Design",
            "updated": "2023-04-14T02:04:00+0000"
        },
        {
            "bbclassextend": "native nativesdk",
            "blacklisted": "",
            "bugtracker": "",
            "configopts": "",
            "description": "",
            "filename": "fvp-base-a-aem.bb",
            "filepath": "recipes-devtools/fvp",
            "homepage": "https://developer.arm.com/tools-and-software/simulation-models/fixed-virtual-platforms/arm-ecosystem-models",
            "id": 1752485,
            "inherits": "",
            "layerbranch": 940047,
            "license": "Proprietary & Apache-2.0 & Python-2.0 & GPL-3.0-with-GCC-exception & Zlib & NCSA & LGPL-2.0-or-later & MIT & BSD-3-Clause",
            "pe": "",
            "pn": "fvp-base-a-aem",
            "pr": "r0",
            "provides": "fvp-base-a-aem ",
            "pv": "11.17.21",
            "section": "base",
            "srcrev": "",
            "summary": "Arm Fixed Virtual Platform - Armv-A Base RevC Architecture Envelope Model FVP",
            "updated": "2023-04-14T02:04:00+0000"
        },
        {
            "bbclassextend": "native nativesdk",
            "blacklisted": "",
            "bugtracker": "",
            "configopts": "",
            "description": "",
            "filename": "fvp-base-r-aem_11.19.14.bb",
            "filepath": "recipes-devtools/fvp",
            "homepage": "https://developer.arm.com/tools-and-software/simulation-models/fixed-virtual-platforms/arm-ecosystem-models",
            "id": 1752486,
            "inherits": "",
            "layerbranch": 940047,
            "license": "Proprietary & Apache-2.0 & Python-2.0 & GPL-3.0-with-GCC-exception & Zlib & NCSA & LGPL-2.0-or-later & MIT & BSD-3-Clause",
            "pe": "",
            "pn": "fvp-base-r-aem",
            "pr": "r0",
            "provides": "fvp-base-r-aem ",
            "pv": "11.19.14",
            "section": "base",
            "srcrev": "",
            "summary": "Arm Fixed Virtual Platform - Armv8-R Base Architecture Envelope Model FVP",
            "updated": "2023-04-14T02:04:00+0000"
        },
        {
            "bbclassextend": "native nativesdk",
            "blacklisted": "",
            "bugtracker": "",
            "configopts": "",
            "description": "",
            "filename": "fvp-corstone500.bb",
            "filepath": "recipes-devtools/fvp",
            "homepage": "https://developer.arm.com/tools-and-software/open-source-software/arm-platforms-software/arm-ecosystem-fvps",
            "id": 1752487,
            "inherits": "",
            "layerbranch": 940047,
            "license": "Proprietary & Apache-2.0 & Python-2.0 & GPL-3.0-with-GCC-exception & Zlib & NCSA & LGPL-2.0-or-later & MIT & BSD-3-Clause",
            "pe": "",
            "pn": "fvp-corstone500",
            "pr": "r0",
            "provides": "fvp-corstone500 ",
            "pv": "11.12.59",
            "section": "base",
            "srcrev": "",
            "summary": "Arm Fixed Virtual Platform - Corstone-500 Ecosystem Reference Design",
            "updated": "2023-04-14T02:04:00+0000"
        },
        {
            "bbclassextend": "native",
            "blacklisted": "",
            "bugtracker": "",
            "configopts": "",
            "description": "",
            "filename": "opencsd_1.2.0.bb",
            "filepath": "recipes-devtools/opencsd",
            "homepage": "https://github.com/Linaro/OpenCSD",
            "id": 1752488,
            "inherits": "",
            "layerbranch": 940047,
            "license": "BSD-3-Clause",
            "pe": "",
            "pn": "opencsd",
            "pr": "r0",
            "provides": "opencsd ",
            "pv": "1.2.0",
            "section": "base",
            "srcrev": "dac554d62d514b202174506995afc0e109ef3fea",
            "summary": "OpenCSD - An open source CoreSight(tm) Trace Decode library",
            "updated": "2023-04-14T02:04:00+0000"
        },
        {
            "bbclassextend": "",
            "blacklisted": "",
            "bugtracker": "",
            "configopts": "",
            "description": "Target-side daemon gathering data for ARM Streamline                Performance Analyzer.",
            "filename": "gator-daemon_7.7.0.bb",
            "filepath": "recipes-devtools/gator-daemon",
            "homepage": "https://github.com/ARM-software/gator",
            "id": 1752489,
            "inherits": "",
            "layerbranch": 940047,
            "license": "GPL-2.0-only & LGPL-2.1-or-later & Apache-2.0",
            "pe": "",
            "pn": "gator-daemon",
            "pr": "r0",
            "provides": "gator-daemon ",
            "pv": "7.7.0",
            "section": "base",
            "srcrev": "9d8d75fa08352470c51abc23fe3b314879bd8b78",
            "summary": "DS-5 Streamline Gator daemon",
            "updated": "2023-04-14T02:04:00+0000"
        },
        {
            "bbclassextend": "",
            "blacklisted": "",
            "bugtracker": "",
            "configopts": " --with-kernel-dir=/tmp/tmph2dtc80k/tmp-glibc/work/qemux86-oe-linux/boot-wrapper-aarch64/gitX-r0/kernel --with-dtb=/tmp/tmph2dtc80k/tmp-glibc/work/qemux86-oe-linux/boot-wrapper-aarch64/gitX-r0/kernel/dummy.dtb --with-cmdline=\\\"\\\" --enable-psci --enable-gicv3 ",
            "description": "",
            "filename": "boot-wrapper-aarch64_git.bb",
            "filepath": "recipes-bsp/boot-wrapper-aarch64",
            "homepage": "",
            "id": 1752490,
            "inherits": "autotools deploy siteconfig siteinfo",
            "layerbranch": 940047,
            "license": "BSD-3-Clause",
            "pe": "",
            "pn": "boot-wrapper-aarch64",
            "pr": "r0",
            "provides": "boot-wrapper-aarch64 ",
            "pv": "gitX",
            "section": "base",
            "srcrev": "1044c77062573985f7c994c3b6cef5695f57e955",
            "summary": "Linux aarch64 boot wrapper with FDT support",
            "updated": "2023-04-14T02:04:00+0000"
        },
        {
            "bbclassextend": "",
            "blacklisted": "",
            "bugtracker": "",
            "configopts": "",
            "description": "A reference Secure Partition Manager (SPM) for systems that implement the Armv8.4-A Secure-EL2 extension",
            "filename": "hafnium_2.6.bb",
            "filepath": "recipes-bsp/hafnium",
            "homepage": "",
            "id": 1752491,
            "inherits": "deploy pkgconfig python3-dir python3native",
            "layerbranch": 940047,
            "license": "BSD-3-Clause & GPL-2.0-only",
            "pe": "",
            "pn": "hafnium",
            "pr": "r0",
            "provides": "hafnium ",
            "pv": "2.6",
            "section": "base",
            "srcrev": "55b74f893948dd08d2782dd8fa9e903c143a6704",
            "summary": "Hafnium",
            "updated": "2023-04-14T02:04:00+0000"
        },
        {
            "bbclassextend": "",
            "blacklisted": "",
            "bugtracker": "",
            "configopts": " -DTFM_TOOLCHAIN_FILE=/tmp/tmph2dtc80k/tmp-glibc/work/qemux86-oe-linux/trusted-firmware-m/1.5.0-r0/git/tfm/toolchain_GNUARM.cmake -DFETCHCONTENT_FULLY_DISCONNECTED=ON -DTFM_PLATFORM=  -DCMAKE_VERBOSE_MAKEFILE:BOOL=ON -DMBEDCRYPTO_PATH=/tmp/tmph2dtc80k/tmp-glibc/work/qemux86-oe-linux/trusted-firmware-m/1.5.0-r0/git/tfm/../mbedtls -DTFM_TEST_REPO_PATH=/tmp/tmph2dtc80k/tmp-glibc/work/qemux86-oe-linux/trusted-firmware-m/1.5.0-r0/git/tfm/../tf-m-tests -DMCUBOOT_PATH=/tmp/tmph2dtc80k/tmp-glibc/work/qemux86-oe-linux/trusted-firmware-m/1.5.0-r0/git/tfm/../mcuboot",
            "description": "Trusted Firmware-M",
            "filename": "trusted-firmware-m_1.5.0.bb",
            "filepath": "recipes-bsp/trusted-firmware-m",
            "homepage": "https://git.trustedfirmware.org/trusted-firmware-m.git",
            "id": 1752492,
            "inherits": "deploy python3-dir python3native",
            "layerbranch": 940047,
            "license": "BSD-3-Clause & Apache-2.0",
            "pe": "",
            "pn": "trusted-firmware-m",
            "pr": "r0",
            "provides": "trusted-firmware-m virtual/trusted-firmware-m",
            "pv": "1.5.0",
            "section": "base",
            "srcrev": "",
            "summary": "Trusted Firmware for Cortex-M",
            "updated": "2023-04-14T02:04:00+0000"
        },
        {
            "bbclassextend": "",
            "blacklisted": "",
            "bugtracker": "",
            "configopts": "",
            "description": "Trusted Firmware-A tests(aka TFTF)",
            "filename": "tf-a-tests_2.6.bb",
            "filepath": "recipes-bsp/trusted-firmware-a",
            "homepage": "",
            "id": 1752493,
            "inherits": "deploy",
            "layerbranch": 940047,
            "license": "BSD-3-Clause & NCSA",
            "pe": "",
            "pn": "tf-a-tests",
            "pr": "r0",
            "provides": "tf-a-tests ",
            "pv": "2.6+gitX",
            "section": "base",
            "srcrev": "af5a517ae9f295455122109100fe5d55668e8eaf",
            "summary": "",
            "updated": "2023-04-14T02:04:01+0000"
        },
        {
            "bbclassextend": "",
            "blacklisted": "",
            "bugtracker": "",
            "configopts": "",
            "description": "Trusted Firmware-A",
            "filename": "trusted-firmware-a_2.7.bb",
            "filepath": "recipes-bsp/trusted-firmware-a",
            "homepage": "",
            "id": 1752494,
            "inherits": "deploy",
            "layerbranch": 940047,
            "license": "BSD-3-Clause & MIT",
            "pe": "",
            "pn": "trusted-firmware-a",
            "pr": "r0",
            "provides": "trusted-firmware-a ",
            "pv": "2.7",
            "section": "base",
            "srcrev": "",
            "summary": "",
            "updated": "2023-04-14T02:04:01+0000"
        },
        {
            "bbclassextend": "",
            "blacklisted": "",
            "bugtracker": "",
            "configopts": "",
            "description": "Trusted Firmware-A",
            "filename": "trusted-firmware-a_2.6.bb",
            "filepath": "recipes-bsp/trusted-firmware-a",
            "homepage": "",
            "id": 1752495,
            "inherits": "deploy",
            "layerbranch": 940047,
            "license": "BSD-3-Clause & MIT",
            "pe": "",
            "pn": "trusted-firmware-a",
            "pr": "r0",
            "provides": "trusted-firmware-a ",
            "pv": "2.6",
            "section": "base",
            "srcrev": "",
            "summary": "",
            "updated": "2023-04-14T02:04:01+0000"
        },
        {
            "bbclassextend": "",
            "blacklisted": "",
            "bugtracker": "",
            "configopts": "",
            "description": "Firmware for SCP and MCP software reference implementation",
            "filename": "scp-firmware_2.9.0.bb",
            "filepath": "recipes-bsp/scp-firmware",
            "homepage": "https://github.com/ARM-software/SCP-firmware",
            "id": 1752496,
            "inherits": "deploy",
            "layerbranch": 940047,
            "license": "BSD-3-Clause & Apache-2.0",
            "pe": "",
            "pn": "scp-firmware",
            "pr": "r0",
            "provides": "scp-firmware  virtual/control-processor-firmware",
            "pv": "2.9.0",
            "section": "base",
            "srcrev": "77ffab90a9f6071850475087cc5d40610c621126",
            "summary": "SCP and MCP Firmware",
            "updated": "2023-04-14T02:04:01+0000"
        },
        {
            "bbclassextend": "",
            "blacklisted": "",
            "bugtracker": "",
            "configopts": "",
            "description": "Firmware for SCP and MCP software reference implementation",
            "filename": "scp-firmware_2.10.0.bb",
            "filepath": "recipes-bsp/scp-firmware",
            "homepage": "https://github.com/ARM-software/SCP-firmware",
            "id": 1752497,
            "inherits": "deploy",
            "layerbranch": 940047,
            "license": "BSD-3-Clause & Apache-2.0",
            "pe": "",
            "pn": "scp-firmware",
            "pr": "r0",
            "provides": "scp-firmware  virtual/control-processor-firmware",
            "pv": "2.10.0",
            "section": "base",
            "srcrev": "673d014f3861ad81cc5ab06d2884a314a610799b",
            "summary": "SCP and MCP Firmware",
            "updated": "2023-04-14T02:04:01+0000"
        },
        {
            "bbclassextend": "",
            "blacklisted": "",
            "bugtracker": "",
            "configopts": "",
            "description": "UEFI EDK2 Firmware for Arm reference platforms",
            "filename": "edk2-firmware_202202.bb",
            "filepath": "recipes-bsp/uefi",
            "homepage": "https://github.com/tianocore/edk2",
            "id": 1752498,
            "inherits": "deploy",
            "layerbranch": 940047,
            "license": "BSD-2-Clause-Patent",
            "pe": "",
            "pn": "edk2-firmware",
            "pr": "r0",
            "provides": "edk2-firmware virtual/bootloader",
            "pv": "202202",
            "section": "base",
            "srcrev": "",
            "summary": "UEFI EDK2 Firmware",
            "updated": "2023-04-14T02:04:01+0000"
        },
        {
            "bbclassextend": "",
            "blacklisted": "",
            "bugtracker": "",
            "configopts": "",
            "description": "UEFI EDK2 Firmware for Arm reference platforms",
            "filename": "sbsa-acs_3.1.bb",
            "filepath": "recipes-bsp/uefi",
            "homepage": "https://github.com/tianocore/edk2",
            "id": 1752499,
            "inherits": "deploy",
            "layerbranch": 940047,
            "license": "BSD-2-Clause-Patent & Apache-2.0",
            "pe": "",
            "pn": "sbsa-acs",
            "pr": "r0",
            "provides": "sbsa-acs ",
            "pv": "3.1",
            "section": "base",
            "srcrev": "",
            "summary": "UEFI EDK2 Firmware",
            "updated": "2023-04-14T02:04:01+0000"
        },
        {
            "bbclassextend": "",
            "blacklisted": "",
            "bugtracker": "",
            "configopts": "",
            "description": "",
            "filename": "secure-partitions_git.bb",
            "filepath": "recipes-security/trusted-services",
            "homepage": "https://trusted-services.readthedocs.io/en/latest/index.html",
            "id": 1752500,
            "inherits": "deploy python3-dir python3native",
            "layerbranch": 940047,
            "license": "Apache-2.0 & BSD-3-Clause & Zlib",
            "pe": "",
            "pn": "secure-partitions",
            "pr": "r0",
            "provides": "secure-partitions ",
            "pv": "0.0+gitX",
            "section": "base",
            "srcrev": "",
            "summary": "Trusted Services secure partitions",
            "updated": "2023-04-14T02:04:01+0000"
        },
        {
            "bbclassextend": "",
            "blacklisted": "",
            "bugtracker": "",
            "configopts": "",
            "description": "TCG reference implementation of the TPM 2.0 Specification.",
            "filename": "optee-ftpm_git.bb",
            "filepath": "recipes-security/optee-ftpm",
            "homepage": "https://github.com/microsoft/ms-tpm-20-ref/",
            "id": 1752501,
            "inherits": "deploy python3-dir python3native",
            "layerbranch": 940047,
            "license": "MIT",
            "pe": "",
            "pn": "optee-ftpm",
            "pr": "r0",
            "provides": "optee-ftpm ",
            "pv": "git",
            "section": "base",
            "srcrev": "d638536d0fe01acd5e39ffa1bd100b3da82d92c7",
            "summary": "OPTEE fTPM Microsoft TA",
            "updated": "2023-04-14T02:04:01+0000"
        },
        {
            "bbclassextend": "",
            "blacklisted": "",
            "bugtracker": "",
            "configopts": "     -DBUILD_SHARED_LIBS=ON     -DCFG_TEE_FS_PARENT_PATH='/var/lib/tee'  ",
            "description": "Open Portable Trusted Execution Environment - Normal World Client side of the TEE",
            "filename": "optee-client_3.14.0.bb",
            "filepath": "recipes-security/optee",
            "homepage": "https://www.op-tee.org/",
            "id": 1752502,
            "inherits": "cmake systemd update-rc.d",
            "layerbranch": 940047,
            "license": "BSD-2-Clause",
            "pe": "",
            "pn": "optee-client",
            "pr": "r0",
            "provides": "optee-client ",
            "pv": "3.14.0",
            "section": "base",
            "srcrev": "06e1b32f6a7028e039c625b07cfc25fda0c17d53",
            "summary": "OP-TEE Client API",
            "updated": "2023-04-14T02:04:01+0000"
        },
        {
            "bbclassextend": "",
            "blacklisted": "",
            "bugtracker": "",
            "configopts": "",
            "description": "Open Portable Trusted Execution Environment - Sample Applications",
            "filename": "optee-examples_3.16.0.bb",
            "filepath": "recipes-security/optee",
            "homepage": "https://github.com/linaro-swg/optee_examples",
            "id": 1752503,
            "inherits": "python3-dir python3native",
            "layerbranch": 940047,
            "license": "BSD-2-Clause",
            "pe": "",
            "pn": "optee-examples",
            "pr": "r0",
            "provides": "optee-examples ",
            "pv": "3.16.0",
            "section": "base",
            "srcrev": "65fc74309e12189ad5b6ce3ffec37c8011088a5a",
            "summary": "OP-TEE examples",
            "updated": "2023-04-14T02:04:01+0000"
        },
        {
            "bbclassextend": "",
            "blacklisted": "",
            "bugtracker": "",
            "configopts": "",
            "description": "OP-TEE TA devkit for build TAs",
            "filename": "optee-os-tadevkit_3.16.0.bb",
            "filepath": "recipes-security/optee",
            "homepage": "https://www.op-tee.org/",
            "id": 1752504,
            "inherits": "deploy python3-dir python3native",
            "layerbranch": 940047,
            "license": "BSD-2-Clause",
            "pe": "",
            "pn": "optee-os-tadevkit",
            "pr": "r0",
            "provides": "optee-os-tadevkit ",
            "pv": "3.16.0",
            "section": "base",
            "srcrev": "d0b742d1564834dac903f906168d7357063d5459",
            "summary": "OP-TEE Trusted OS TA devkit",
            "updated": "2023-04-14T02:04:01+0000"
        },
        {
            "bbclassextend": "",
            "blacklisted": "",
            "bugtracker": "",
            "configopts": "     -DBUILD_SHARED_LIBS=ON     -DCFG_TEE_FS_PARENT_PATH='/var/lib/tee'  ",
            "description": "Open Portable Trusted Execution Environment - Normal World Client side of the TEE",
            "filename": "optee-client_3.16.0.bb",
            "filepath": "recipes-security/optee",
            "homepage": "https://www.op-tee.org/",
            "id": 1752505,
            "inherits": "cmake systemd update-rc.d",
            "layerbranch": 940047,
            "license": "BSD-2-Clause",
            "pe": "",
            "pn": "optee-client",
            "pr": "r0",
            "provides": "optee-client ",
            "pv": "3.16.0",
            "section": "base",
            "srcrev": "06db73b3f3fdb8d23eceaedbc46c49c0b45fd1e2",
            "summary": "OP-TEE Client API",
            "updated": "2023-04-14T02:04:01+0000"
        },
        {
            "bbclassextend": "",
            "blacklisted": "",
            "bugtracker": "",
            "configopts": "",
            "description": "Open Portable Trusted Execution Environment - Development Kit to run secure partitions",
            "filename": "optee-spdevkit_git.bb",
            "filepath": "recipes-security/optee",
            "homepage": "https://www.op-tee.org/",
            "id": 1752506,
            "inherits": "deploy python3-dir python3native",
            "layerbranch": 940047,
            "license": "BSD-2-Clause",
            "pe": "",
            "pn": "optee-spdevkit",
            "pr": "r0",
            "provides": "optee-spdevkit ",
            "pv": "3.10+gitX",
            "section": "base",
            "srcrev": "f9de2c9520ed97b89760cc4c99424aae440b63f4",
            "summary": "OP-TEE Secure Partion Development Kit",
            "updated": "2023-04-14T02:04:02+0000"
        },
        {
            "bbclassextend": "",
            "blacklisted": "",
            "bugtracker": "",
            "configopts": "",
            "description": "Open Portable Trusted Execution Environment - Trusted side of the TEE",
            "filename": "optee-os_3.14.0.bb",
            "filepath": "recipes-security/optee",
            "homepage": "https://www.op-tee.org/",
            "id": 1752507,
            "inherits": "deploy python3-dir python3native",
            "layerbranch": 940047,
            "license": "BSD-2-Clause",
            "pe": "",
            "pn": "optee-os",
            "pr": "r0",
            "provides": "optee-os ",
            "pv": "3.14.0",
            "section": "base",
            "srcrev": "d21befa5e53eae9db469eba1685f5aa5c6f92c2f",
            "summary": "OP-TEE Trusted OS",
            "updated": "2023-04-14T02:04:02+0000"
        },
        {
            "bbclassextend": "",
            "blacklisted": "",
            "bugtracker": "",
            "configopts": "",
            "description": "Open Portable Trusted Execution Environment - Trusted side of the TEE",
            "filename": "optee-os_3.16.0.bb",
            "filepath": "recipes-security/optee",
            "homepage": "https://www.op-tee.org/",
            "id": 1752508,
            "inherits": "deploy python3-dir python3native",
            "layerbranch": 940047,
            "license": "BSD-2-Clause",
            "pe": "",
            "pn": "optee-os",
            "pr": "r0",
            "provides": "optee-os ",
            "pv": "3.16.0",
            "section": "base",
            "srcrev": "d0b742d1564834dac903f906168d7357063d5459",
            "summary": "OP-TEE Trusted OS",
            "updated": "2023-04-14T02:04:02+0000"
        },
        {
            "bbclassextend": "",
            "blacklisted": "",
            "bugtracker": "",
            "configopts": "",
            "description": "Open Portable Trusted Execution Environment - Test suite",
            "filename": "optee-test_3.16.0.bb",
            "filepath": "recipes-security/optee",
            "homepage": "https://www.op-tee.org/",
            "id": 1752509,
            "inherits": "ptest python3-dir python3native",
            "layerbranch": 940047,
            "license": "BSD-2-Clause & GPL-2.0-only",
            "pe": "",
            "pn": "optee-test",
            "pr": "r0",
            "provides": "optee-test ",
            "pv": "3.16.0",
            "section": "base",
            "srcrev": "1cf0e6d2bdd1145370033d4e182634458528579d",
            "summary": "OP-TEE sanity testsuite",
            "updated": "2023-04-14T02:04:02+0000"
        },
        {
            "bbclassextend": "",
            "blacklisted": "",
            "bugtracker": "",
            "configopts": "",
            "description": "This out-of-tree kernel module exposes FF-A operations to user space used for development purposes",
            "filename": "ffa-debugfs-mod_2.1.0.bb",
            "filepath": "recipes-kernel/ffa-debugfs",
            "homepage": "",
            "id": 1752510,
            "inherits": "kernel-arch kernel-module-split module module-base pkgconfig",
            "layerbranch": 940047,
            "license": "GPL-2.0-only",
            "pe": "",
            "pn": "ffa-debugfs-mod",
            "pr": "r0",
            "provides": "ffa-debugfs-mod ",
            "pv": "2.1.0",
            "section": "base",
            "srcrev": "45eb7c1484ae9bea2bbd0583b86beb55b627073b",
            "summary": "FF-A Debugfs Linux kernel module",
            "updated": "2023-04-14T02:04:02+0000"
        },
        {
            "bbclassextend": "",
            "blacklisted": "",
            "bugtracker": "",
            "configopts": "",
            "description": "Linux Android Common Kernel",
            "filename": "linux-arm64-ack_5.10.bb",
            "filepath": "recipes-kernel/linux",
            "homepage": "https://www.yoctoproject.org/",
            "id": 1752511,
            "inherits": "cml1 deploy image-artifact-names kernel kernel-arch kernel-artifact-names kernel-devicetree kernel-module-split kernel-uboot kernel-uimage kernel-yocto linux-kernel-base pkgconfig",
            "layerbranch": 940047,
            "license": "GPL-2.0-only",
            "pe": "",
            "pn": "linux-arm64-ack",
            "pr": "r0",
            "provides": "linux-arm64-ack  virtual/kernel",
            "pv": "5.10",
            "section": "kernel",
            "srcrev": "3d371f087c953c0e08a228169d4e5c44aea99416",
            "summary": "Linux kernel",
            "updated": "2023-04-14T02:04:02+0000"
        }
    ],
    "wrtemplates": []
}